terminal2048/__init__.py
terminal2048/term_2048.py
terminal2048-0.1.0.dist-info/METADATA
terminal2048-0.1.0.dist-info/WHEEL
terminal2048-0.1.0.dist-info/entry_points.txt
terminal2048-0.1.0.dist-info/RECORD
