Metadata-Version: 2.1
Name: terminal2048
Version: 0.1.0
Summary: 2048 for the terminal. Inspired by Gabriele Cirulli's 2048.
Author: Evan Jones
Author-email: evan_jones@mac.com
Requires-Python: >=3.10,<4.0
Classifier: Programming Language :: Python :: 3
Classifier: Programming Language :: Python :: 3.10
Classifier: Programming Language :: Python :: 3.11
Requires-Dist: blessed (>=1.20.0,<2.0.0)
